keras_vit/__init__.py
keras_vit/config.py
keras_vit/layers.py
keras_vit/utils.py
keras_vit/vit.py
keras_vit-1.0.1.dist-info/LICENSE.txt
keras_vit-1.0.1.dist-info/METADATA
keras_vit-1.0.1.dist-info/WHEEL
keras_vit-1.0.1.dist-info/top_level.txt
keras_vit-1.0.1.dist-info/RECORD
