Metadata-Version: 2.1
Name: keras-vit
Version: 1.0.1
Summary: Implementation of ViT model based on Keras
Home-page: https://github.com/djsaber/Keras-ViT
Author: djsaber
Author-email: 479719615@qq.com
License: UNKNOWN
Platform: UNKNOWN
Classifier: Programming Language :: Python :: 3
Classifier: License :: OSI Approved :: MIT License
Classifier: Operating System :: OS Independent
Requires-Python: >=3.7
